ask_lib/__init__.py
ask_lib/ask.py
ask_lib/ask_flag.py
ask_lib/ask_result.py
ask_lib-2.0.1.dist-info/METADATA
ask_lib-2.0.1.dist-info/WHEEL
ask_lib-2.0.1.dist-info/RECORD
