Metadata-Version: 2.1
Name: ask-lib
Version: 2.0.1
Summary: Utility function to ask for user's confirmation in a CLI
License: MIT
Author: CallMePixelMan
Requires-Python: >=3.8,<4.0
Classifier: License :: OSI Approved :: MIT License
Classifier: Programming Language :: Python :: 3
Classifier: Programming Language :: Python :: 3.8
Classifier: Programming Language :: Python :: 3.9
Classifier: Programming Language :: Python :: 3.10
Classifier: Programming Language :: Python :: 3.11
Requires-Dist: pytest-cov (>=4.1.0,<5.0.0)
